initial_report/__init__.py
initial_report/__main__.py
initial_report/metrics.py
initial_report/plot.py
initial_report/report.py
initial_report/templates/base.html
initial_report-0.1.dist-info/LICENSE.md
initial_report-0.1.dist-info/METADATA
initial_report-0.1.dist-info/WHEEL
initial_report-0.1.dist-info/entry_points.txt
initial_report-0.1.dist-info/top_level.txt
initial_report-0.1.dist-info/RECORD
