Metadata-Version: 2.1
Name: initial-report
Version: 0.1
Summary: High-level dashboard views of graphs and districting plans
Home-page: https://github.com/mggg/initial-report
Author: Max Hully
Author-email: max@mggg.org
License: UNKNOWN
Platform: UNKNOWN
Classifier: Programming Language :: Python :: 3.6
Classifier: Programming Language :: Python :: 3.7
Classifier: Operating System :: OS Independent
Classifier: License :: OSI Approved :: MIT License
Requires-Dist: numpy
Requires-Dist: pandas
Requires-Dist: geopandas
Requires-Dist: shapely
Requires-Dist: maup
Requires-Dist: gerrychain
Requires-Dist: matplotlib
Requires-Dist: jinja2
